monochrome/__init__.py
monochrome/__main__.py
monochrome/_version.py
monochrome/data/bin/Monochrome.exe
monochrome/fbs/__init__.py
monochrome/fbs/Array3DataChunkf.py
monochrome/fbs/Array3DataChunku16.py
monochrome/fbs/Array3DataChunku8.py
monochrome/fbs/Array3Meta.py
monochrome/fbs/Array3MetaFlow.py
monochrome/fbs/ArrayDataType.py
monochrome/fbs/BitRange.py
monochrome/fbs/CloseVideo.py
monochrome/fbs/Color.py
monochrome/fbs/ColorMap.py
monochrome/fbs/Data.py
monochrome/fbs/DictEntry.py
monochrome/fbs/Filepaths.py
monochrome/fbs/OpacityFunction.py
monochrome/fbs/PointsVideo.py
monochrome/fbs/Quit.py
monochrome/fbs/Root.py
monochrome/fbs/VideoExport.py
monochrome/fbs/VideoExportFormat.py
monochrome/ipc.py
monochrome-2025.9.11.dist-info/METADATA
monochrome-2025.9.11.dist-info/WHEEL
monochrome-2025.9.11.dist-info/entry_points.txt
monochrome-2025.9.11.dist-info/licenses/LICENSE.md
monochrome-2025.9.11.dist-info/RECORD
