Metadata-Version: 2.2
Name: monochrome
Version: 2025.9.11
Summary: Viewer for monochromatic video data
Author-Email: Jan Lebert <mail@janlebert.com>
Classifier: Development Status :: 5 - Production/Stable
Classifier: Intended Audience :: Science/Research
Classifier: License :: OSI Approved :: MIT License
Classifier: Operating System :: Microsoft :: Windows
Classifier: Operating System :: MacOS
Classifier: Operating System :: POSIX
Classifier: Programming Language :: C++
Classifier: Programming Language :: Python :: 3
Classifier: Topic :: Desktop Environment
Classifier: Topic :: Multimedia :: Video :: Display
Classifier: Topic :: Scientific/Engineering :: Visualization
Project-URL: Documentation, https://monochrome.readthedocs.io
Project-URL: Repository, https://github.com/sitic/monochrome
Requires-Python: >=3.6
Requires-Dist: numpy
Requires-Dist: flatbuffers>=23.5.26
Provides-Extra: test
Requires-Dist: pytest; extra == "test"
Provides-Extra: docs
Requires-Dist: sphinx==8.1.3; extra == "docs"
Requires-Dist: sphinxcontrib-napoleon; extra == "docs"
Requires-Dist: sphinxcontrib-bibtex; extra == "docs"
Requires-Dist: sphinxcontrib-video; extra == "docs"
Requires-Dist: sphinx-autobuild; extra == "docs"
Requires-Dist: sphinx-copybutton; extra == "docs"
Requires-Dist: sphinx-codeautolink; extra == "docs"
Requires-Dist: furo; extra == "docs"
Requires-Dist: myst_nb>=1.0.0; extra == "docs"
Requires-Dist: jupytext; extra == "docs"
Requires-Dist: jupyter-cache; extra == "docs"
Requires-Dist: sphinx-remove-toctrees; extra == "docs"
Requires-Dist: sphinx-design; extra == "docs"
Requires-Dist: enum-tools[sphinx]; extra == "docs"
Requires-Dist: opticalmapping[all]; extra == "docs"
